furigana4epub/__init__.py
furigana4epub/furigana4epub.py
furigana4epub/version.py
furigana4epub/yomituki.py
furigana4epub-1.0.2.dist-info/LICENSE
furigana4epub-1.0.2.dist-info/METADATA
furigana4epub-1.0.2.dist-info/WHEEL
furigana4epub-1.0.2.dist-info/entry_points.txt
furigana4epub-1.0.2.dist-info/top_level.txt
furigana4epub-1.0.2.dist-info/RECORD
