Metadata-Version: 2.1
Name: furigana4epub
Version: 1.0.2
Summary: A Python script to adding/removing furigana for Japanese epub books.
Home-page: https://github.com/Mumumu4/furigana4epub
Author: Mumumu
Author-email: 30195921+Mumumu4@users.noreply.github.com
License: MIT
Keywords: Japanese,readings,epub,furigana
Platform: UNKNOWN
Classifier: License :: OSI Approved :: MIT License
Classifier: Natural Language :: Japanese
Classifier: Topic :: Text Processing :: Linguistic
Classifier: Environment :: Console
Requires-Python: <4,>=3.6
License-File: LICENSE
Requires-Dist: lxml
Requires-Dist: fugashi
Requires-Dist: unidic-lite
Requires-Dist: beautifulsoup4 (>=4.9.1)
